[
  {
    "outbound flight": "(PMI-OPO) Mar., 14 May.",
    "return flight": "(OPO-PMI) Mié., 15 May.",
    "price": "64€"
  },
  {
    "outbound flight": "(PMI-OPO) Mié., 05 Jun.",
    "return flight": null,
    "price": "25€"
  },
  {
    "outbound flight": "(PMI-OPO) Mar., 28 May.",
    "return flight": "(OPO-PMI) Vie., 31 May.",
    "price": "141€"
  },
  {
    "outbound flight": "(PMI-OPO) Vie., 10 May.",
    "return flight": "(OPO-PMI) Sáb., 11 May.",
    "price": "154€"
  },
  {
    "outbound flight": "(PMI-OPO) Vie., 17 May.",
    "return flight": "(OPO-PMI) Dom., 19 May.",
    "price": "252€"
  },
  {
    "outbound flight": "(PMI-OPO) Sáb., 25 May.",
    "return flight": "(OPO-PMI) Dom., 26 May.",
    "price": "216€"
  }
]