[
  {
    "outbound flight": "(PMI-OPO) Mar., 03 Sept.",
    "return flight": "(OPO-PMI) Mié., 04 Sept.",
    "price": "161€"
  },
  {
    "outbound flight": "(PMI-OPO) Sáb., 09 Nov.",
    "return flight": null,
    "price": "22€"
  },
  {
    "outbound flight": "(PMI-OPO) Mar., 17 Sept.",
    "return flight": "(OPO-PMI) Jue., 19 Sept.",
    "price": "116€"
  },
  {
    "outbound flight": "(PMI-OPO) Lun., 26 Ago.",
    "return flight": "(OPO-PMI) Jue., 29 Ago.",
    "price": "248€"
  },
  {
    "outbound flight": "(PMI-OPO) Jue., 05 Sept.",
    "return flight": "(OPO-PMI) Lun., 09 Sept.",
    "price": "188€"
  },
  {
    "outbound flight": "(PMI-OPO) Mar., 10 Sept.",
    "return flight": "(OPO-PMI) Vie., 13 Sept.",
    "price": "188€"
  }
]